seapopym/__init__.py
seapopym/configuration/__init__.py
seapopym/configuration/acidity/__init__.py
seapopym/configuration/acidity/configuration.py
seapopym/configuration/acidity/forcing_parameter.py
seapopym/configuration/acidity/functional_group_parameter.py
seapopym/configuration/acidity_bed/__init__.py
seapopym/configuration/acidity_bed/configuration.py
seapopym/configuration/acidity_bed/functional_group_parameter.py
seapopym/configuration/acidity_bed_bh/__init__.py
seapopym/configuration/acidity_bed_bh/configuration.py
seapopym/configuration/acidity_bed_bh/functional_group_parameter.py
seapopym/configuration/acidity_bed_bh_pft/__init__.py
seapopym/configuration/acidity_bed_bh_pft/configuration.py
seapopym/configuration/acidity_bed_bh_pft/forcing_parameter.py
seapopym/configuration/acidity_bed_bh_pft/functional_group_parameter.py
seapopym/configuration/no_transport/__init__.py
seapopym/configuration/no_transport/configuration.py
seapopym/configuration/no_transport/forcing_parameter.py
seapopym/configuration/no_transport/functional_group_parameter.py
seapopym/configuration/no_transport/kernel_parameter.py
seapopym/configuration/validation.py
seapopym/core/__init__.py
seapopym/core/kernel.py
seapopym/core/template.py
seapopym/function/__init__.py
seapopym/function/apply_coefficient_to_primary_production.py
seapopym/function/apply_food_efficiency_to_primary_production.py
seapopym/function/apply_mask_to_state.py
seapopym/function/apply_survival_rate_to_recruitment.py
seapopym/function/average_acidity.py
seapopym/function/average_temperature.py
seapopym/function/berverton_holt.py
seapopym/function/biomass.py
seapopym/function/cell_area.py
seapopym/function/compiled_functions/__init__.py
seapopym/function/compiled_functions/beverton_holt.py
seapopym/function/compiled_functions/biomass_compiled_functions.py
seapopym/function/compiled_functions/production_compiled_functions.py
seapopym/function/day_length.py
seapopym/function/global_mask.py
seapopym/function/limits.py
seapopym-0.0.2.5.8.dist-info/METADATA
seapopym-0.0.2.5.8.dist-info/WHEEL
seapopym-0.0.2.5.8.dist-info/licenses/LICENSE
seapopym-0.0.2.5.8.dist-info/RECORD
