Metadata-Version: 2.4
Name: seapopym
Version: 0.0.2.5.8
Summary: Seapodym is a Python package that provides models to simulate the dynamics of low and mid trophic level marine ecosystems.
License: GPL-3.0-or-later
License-File: LICENSE
Keywords: oceanography,marine ecosystems,marine biology
Author: Jules Lehodey
Author-email: lehodey.jules+seapopym@gmail.com
Requires-Python: >=3.12,<3.13
Classifier: Topic :: Scientific/Engineering :: Oceanography
Requires-Dist: attrs (>=25.3.0,<26.0.0)
Requires-Dist: cf-xarray (>=0.10.9,<0.11.0)
Requires-Dist: dask (>=2025.9.0,<2026.0.0)
Requires-Dist: distributed (>=2025.9.0,<2026.0.0)
Requires-Dist: numba (>=0.61.2,<0.62.0)
Requires-Dist: pint (>=0.25,<0.26)
Requires-Dist: pint-xarray (>=0.6.0,<0.7.0)
Requires-Dist: pyarrow (>=21.0.0,<22.0.0)
Requires-Dist: xarray (>=2025.9.0,<2026.0.0)
Project-URL: Documentation, https://seapopym.readthedocs.io/en/latest/
Project-URL: Repository, https://github.com/Ash12H/seapopym.git
